CHANGELOG.md
LICENSE
qm/QuantumMachine.py
qm/_QmJobErrors.py
qm/__init__.py
qm/_loc.py
qm/_octaves_container.py
qm/_report.py
qm/_stream_results/__init__.py
qm/_stream_results/_multiple_streams_fetcher.py
qm/_stream_results/_single_stream_fetchers/__init__.py
qm/_stream_results/_single_stream_fetchers/_base_single_stream_fetcher.py
qm/_stream_results/_single_stream_fetchers/_single_stream_multiple_results_fetcher.py
qm/_stream_results/_single_stream_fetchers/_single_stream_single_result_fetcher.py
qm/_stream_results/_streams_manager.py
qm/_stream_results/_utils.py
qm/api/__init__.py
qm/api/base_api.py
qm/api/frontend_api.py
qm/api/info_service_api.py
qm/api/job_manager_api.py
qm/api/job_result_api.py
qm/api/models/__init__.py
qm/api/models/capabilities.py
qm/api/models/channel.py
qm/api/models/compiler.py
qm/api/models/debug_data.py
qm/api/models/devices.py
qm/api/models/info.py
qm/api/models/jobs.py
qm/api/models/quantum_machine.py
qm/api/models/server_details.py
qm/api/server_detector.py
qm/api/simulation_api.py
qm/api/stubs/__init__.py
qm/api/stubs/deprecated_job_manager_stub.py
qm/api/v2/__init__.py
qm/api/v2/base_api_v2.py
qm/api/v2/job_api/__init__.py
qm/api/v2/job_api/element_api.py
qm/api/v2/job_api/element_input_api.py
qm/api/v2/job_api/element_port_api.py
qm/api/v2/job_api/generic_apis.py
qm/api/v2/job_api/job_api.py
qm/api/v2/job_api/job_elements_db.py
qm/api/v2/job_api/simulated_job_api.py
qm/api/v2/job_result_api.py
qm/api/v2/qm_api.py
qm/api/v2/qm_api_old.py
qm/api/v2/qmm_api.py
qm/communication/__init__.py
qm/communication/http_redirection.py
qm/containers/__init__.py
qm/containers/capabilities_container.py
qm/datadog_api.py
qm/elements/__init__.py
qm/elements/element.py
qm/elements/element_inputs.py
qm/elements/element_outputs.py
qm/elements/up_converted_input.py
qm/elements_db.py
qm/exceptions.py
qm/grpc/VERSION
qm/grpc/__init__.py
qm/grpc/compiler/__init__.py
qm/grpc/errors/__init__.py
qm/grpc/frontend/__init__.py
qm_qua-1.2.4.dist-info/LICENSE
qm_qua-1.2.4.dist-info/METADATA
qm_qua-1.2.4.dist-info/WHEEL
qm_qua-1.2.4.dist-info/RECORD
